djangocms_rest_view/__init__.py
djangocms_rest_view/fields.py
djangocms_rest_view/models.py
djangocms_rest_view/routers.py
djangocms_rest_view/serializers.py
djangocms_rest_view/urls.py
djangocms_rest_view/views.py
djangocms_rest_view/client/__init__.py
djangocms_rest_view/client/models.py
djangocms_rest_view/client/urls.py
djangocms_rest_view/client/views.py
djangocms_rest_view/client/static/djangocms_rest/js/app.js
djangocms_rest_view/client/static/djangocms_rest/js/controllers.js
djangocms_rest_view/client/static/djangocms_rest/js/filters.js
djangocms_rest_view/client/static/djangocms_rest/js/rest-client.js
djangocms_rest_view/client/static/partials/home.html
djangocms_rest_view/client/static/partials/inner.html
djangocms_rest_view/client/static/partials/main.html
djangocms_rest_view/client/static/partials/page-detail.html
djangocms_rest_view/client/templates/rest/base.html
djangocms_rest_view-0.1.9.dist-info/DESCRIPTION.rst
djangocms_rest_view-0.1.9.dist-info/LICENSE.txt
djangocms_rest_view-0.1.9.dist-info/METADATA
djangocms_rest_view-0.1.9.dist-info/RECORD
djangocms_rest_view-0.1.9.dist-info/WHEEL
djangocms_rest_view-0.1.9.dist-info/metadata.json
djangocms_rest_view-0.1.9.dist-info/top_level.txt
