Metadata-Version: 2.0
Name: djangocms-rest-view
Version: 0.1.9
Summary: DRF View for django CMS
Home-page: https://github.com/nephila/djangocms-rest-view
Author: Iacopo Spalletti
Author-email: i.spalletti@nephila.it
License: BSD
Keywords: djangocms-rest-view
Platform: UNKNOWN
Classifier: Development Status :: 3 - Alpha
Classifier: Framework :: Django
Classifier: Framework :: Django :: 1.8
Classifier: Framework :: Django :: 1.9
Classifier: Intended Audience :: Developers
Classifier: License :: OSI Approved :: BSD License
Classifier: Natural Language :: English
Classifier: Programming Language :: Python :: 2
Classifier: Programming Language :: Python :: 2.7
Classifier: Programming Language :: Python :: 3
Classifier: Programming Language :: Python :: 3.3
Classifier: Programming Language :: Python :: 3.4
Classifier: Programming Language :: Python :: 3.5
Requires-Dist: djangorestframework
